{"nodes": [{"id": "booking", "label": "booking.py", "file_type": "code", "source_file": "api/routers/booking.py", "source_location": "L1"}, {"id": "booking_get_availability", "label": "get_availability()", "file_type": "code", "source_file": "api/routers/booking.py", "source_location": "L24"}, {"id": "booking_set_availability", "label": "set_availability()", "file_type": "code", "source_file": "api/routers/booking.py", "source_location": "L67"}, {"id": "booking_get_available_slots", "label": "get_available_slots()", "file_type": "code", "source_file": "api/routers/booking.py", "source_location": "L120"}, {"id": "booking_reserve_slot", "label": "reserve_slot()", "file_type": "code", "source_file": "api/routers/booking.py", "source_location": "L317"}, {"id": "booking_get_public_service_info", "label": "get_public_service_info()", "file_type": "code", "source_file": "api/routers/booking.py", "source_location": "L510"}, {"id": "booking_get_available_dates", "label": "get_available_dates()", "file_type": "code", "source_file": "api/routers/booking.py", "source_location": "L560"}, {"id": "booking_cancel_booking", "label": "cancel_booking()", "file_type": "code", "source_file": "api/routers/booking.py", "source_location": "L623"}, {"id": "booking_rationale_1", "label": "Internal booking system endpoints - replaces Calendly dependency", "file_type": "rationale", "source_file": "api/routers/booking.py", "source_location": "L1"}, {"id": "booking_rationale_25", "label": "Get creator's weekly availability schedule", "file_type": "rationale", "source_file": "api/routers/booking.py", "source_location": "L25"}, {"id": "booking_rationale_68", "label": "Set creator's weekly availability.     Body: [{ day_of_week: 0, start_time: \"09:", "file_type": "rationale", "source_file": "api/routers/booking.py", "source_location": "L68"}, {"id": "booking_rationale_126", "label": "Get available slots for a specific date and service.     Uses DEFAULT availabili", "file_type": "rationale", "source_file": "api/routers/booking.py", "source_location": "L126"}, {"id": "booking_rationale_318", "label": "Reserve a booking slot.     Body: {         service_id: string,         date: \"Y", "file_type": "rationale", "source_file": "api/routers/booking.py", "source_location": "L318"}, {"id": "booking_rationale_511", "label": "Get public information about a service for the booking page.     No authenticati", "file_type": "rationale", "source_file": "api/routers/booking.py", "source_location": "L511"}, {"id": "booking_rationale_567", "label": "Get dates with availability for the next 30 days (or specified month).     Uses", "file_type": "rationale", "source_file": "api/routers/booking.py", "source_location": "L567"}], "edges": [{"source": "booking", "target": "fastapi", "relation": "imports_from", "confidence": "EXTRACTED", "source_file": "api/routers/booking.py", "source_location": "L2", "weight": 1.0}, {"source": "booking", "target": "sqlalchemy_orm", "relation": "imports_from", "confidence": "EXTRACTED", "source_file": "api/routers/booking.py", "source_location": "L3", "weight": 1.0}, {"source": "booking", "target": "datetime", "relation": "imports_from", "confidence": "EXTRACTED", "source_file": "api/routers/booking.py", "source_location": "L4", "weight": 1.0}, {"source": "booking", "target": "logging", "relation": "imports", "confidence": "EXTRACTED", "source_file": "api/routers/booking.py", "source_location": "L5", "weight": 1.0}, {"source": "booking", "target": "uuid", "relation": "imports", "confidence": "EXTRACTED", "source_file": "api/routers/booking.py", "source_location": "L6", "weight": 1.0}, {"source": "booking", "target": "api_database", "relation": "imports_from", "confidence": "EXTRACTED", "source_file": "api/routers/booking.py", "source_location": "L9", "weight": 1.0}, {"source": "booking", "target": "api_models", "relation": "imports_from", "confidence": "EXTRACTED", "source_file": "api/routers/booking.py", "source_location": "L10", "weight": 1.0}, {"source": "booking", "target": "database", "relation": "imports_from", "confidence": "EXTRACTED", "source_file": "api/routers/booking.py", "source_location": "L12", "weight": 1.0}, {"source": "booking", "target": "models", "relation": "imports_from", "confidence": "EXTRACTED", "source_file": "api/routers/booking.py", "source_location": "L13", "weight": 1.0}, {"source": "booking", "target": "booking_get_availability", "relation": "contains", "confidence": "EXTRACTED", "source_file": "api/routers/booking.py", "source_location": "L24", "weight": 1.0}, {"source": "booking", "target": "booking_set_availability", "relation": "contains", "confidence": "EXTRACTED", "source_file": "api/routers/booking.py", "source_location": "L67", "weight": 1.0}, {"source": "booking", "target": "booking_get_available_slots", "relation": "contains", "confidence": "EXTRACTED", "source_file": "api/routers/booking.py", "source_location": "L120", "weight": 1.0}, {"source": "booking", "target": "booking_reserve_slot", "relation": "contains", "confidence": "EXTRACTED", "source_file": "api/routers/booking.py", "source_location": "L317", "weight": 1.0}, {"source": "booking", "target": "booking_get_public_service_info", "relation": "contains", "confidence": "EXTRACTED", "source_file": "api/routers/booking.py", "source_location": "L510", "weight": 1.0}, {"source": "booking", "target": "booking_get_available_dates", "relation": "contains", "confidence": "EXTRACTED", "source_file": "api/routers/booking.py", "source_location": "L560", "weight": 1.0}, {"source": "booking", "target": "booking_cancel_booking", "relation": "contains", "confidence": "EXTRACTED", "source_file": "api/routers/booking.py", "source_location": "L623", "weight": 1.0}, {"source": "booking_rationale_1", "target": "booking", "relation": "rationale_for", "confidence": "EXTRACTED", "source_file": "api/routers/booking.py", "source_location": "L1", "weight": 1.0}, {"source": "booking_rationale_25", "target": "booking_get_availability", "relation": "rationale_for", "confidence": "EXTRACTED", "source_file": "api/routers/booking.py", "source_location": "L25", "weight": 1.0}, {"source": "booking_rationale_68", "target": "booking_set_availability", "relation": "rationale_for", "confidence": "EXTRACTED", "source_file": "api/routers/booking.py", "source_location": "L68", "weight": 1.0}, {"source": "booking_rationale_126", "target": "booking_get_available_slots", "relation": "rationale_for", "confidence": "EXTRACTED", "source_file": "api/routers/booking.py", "source_location": "L126", "weight": 1.0}, {"source": "booking_rationale_318", "target": "booking_reserve_slot", "relation": "rationale_for", "confidence": "EXTRACTED", "source_file": "api/routers/booking.py", "source_location": "L318", "weight": 1.0}, {"source": "booking_rationale_511", "target": "booking_get_public_service_info", "relation": "rationale_for", "confidence": "EXTRACTED", "source_file": "api/routers/booking.py", "source_location": "L511", "weight": 1.0}, {"source": "booking_rationale_567", "target": "booking_get_available_dates", "relation": "rationale_for", "confidence": "EXTRACTED", "source_file": "api/routers/booking.py", "source_location": "L567", "weight": 1.0}]}