{"nodes": [{"id": "028_add_gold_examples_table", "label": "028_add_gold_examples_table.py", "file_type": "code", "source_file": "alembic/versions/028_add_gold_examples_table.py", "source_location": "L1"}, {"id": "028_add_gold_examples_table_upgrade", "label": "upgrade()", "file_type": "code", "source_file": "alembic/versions/028_add_gold_examples_table.py", "source_location": "L21"}, {"id": "028_add_gold_examples_table_downgrade", "label": "downgrade()", "file_type": "code", "source_file": "alembic/versions/028_add_gold_examples_table.py", "source_location": "L44"}, {"id": "028_add_gold_examples_table_rationale_1", "label": "add gold_examples table for few-shot prompt injection  Stores high-quality creat", "file_type": "rationale", "source_file": "alembic/versions/028_add_gold_examples_table.py", "source_location": "L1"}], "edges": [{"source": "028_add_gold_examples_table", "target": "alembic", "relation": "imports_from", "confidence": "EXTRACTED", "source_file": "alembic/versions/028_add_gold_examples_table.py", "source_location": "L11", "weight": 1.0}, {"source": "028_add_gold_examples_table", "target": "sqlalchemy", "relation": "imports", "confidence": "EXTRACTED", "source_file": "alembic/versions/028_add_gold_examples_table.py", "source_location": "L12", "weight": 1.0}, {"source": "028_add_gold_examples_table", "target": "sqlalchemy_dialects_postgresql", "relation": "imports_from", "confidence": "EXTRACTED", "source_file": "alembic/versions/028_add_gold_examples_table.py", "source_location": "L13", "weight": 1.0}, {"source": "028_add_gold_examples_table", "target": "028_add_gold_examples_table_upgrade", "relation": "contains", "confidence": "EXTRACTED", "source_file": "alembic/versions/028_add_gold_examples_table.py", "source_location": "L21", "weight": 1.0}, {"source": "028_add_gold_examples_table", "target": "028_add_gold_examples_table_downgrade", "relation": "contains", "confidence": "EXTRACTED", "source_file": "alembic/versions/028_add_gold_examples_table.py", "source_location": "L44", "weight": 1.0}, {"source": "028_add_gold_examples_table_rationale_1", "target": "028_add_gold_examples_table", "relation": "rationale_for", "confidence": "EXTRACTED", "source_file": "alembic/versions/028_add_gold_examples_table.py", "source_location": "L1", "weight": 1.0}]}