{"nodes": [{"id": "preview", "label": "preview.py", "file_type": "code", "source_file": "api/routers/preview.py", "source_location": "L1"}, {"id": "preview_preview_status", "label": "preview_status()", "file_type": "code", "source_file": "api/routers/preview.py", "source_location": "L19"}, {"id": "preview_get_screenshot", "label": "get_screenshot()", "file_type": "code", "source_file": "api/routers/preview.py", "source_location": "L29"}, {"id": "preview_get_link_preview_endpoint", "label": "get_link_preview_endpoint()", "file_type": "code", "source_file": "api/routers/preview.py", "source_location": "L92"}, {"id": "preview_get_instagram_preview", "label": "get_instagram_preview()", "file_type": "code", "source_file": "api/routers/preview.py", "source_location": "L131"}, {"id": "preview_get_youtube_preview", "label": "get_youtube_preview()", "file_type": "code", "source_file": "api/routers/preview.py", "source_location": "L168"}, {"id": "preview_rationale_1", "label": "Link Preview endpoints - Screenshot service for link previews", "file_type": "rationale", "source_file": "api/routers/preview.py", "source_location": "L1"}, {"id": "preview_rationale_20", "label": "Check if screenshot service is available", "file_type": "rationale", "source_file": "api/routers/preview.py", "source_location": "L20"}, {"id": "preview_rationale_35", "label": "Capture a screenshot of any URL.     Uses Playwright if available, otherwise Mic", "file_type": "rationale", "source_file": "api/routers/preview.py", "source_location": "L35"}, {"id": "preview_rationale_95", "label": "Get a smart preview of a URL (auto-detects platform).      Supports:     - Insta", "file_type": "rationale", "source_file": "api/routers/preview.py", "source_location": "L95"}, {"id": "preview_rationale_134", "label": "Get preview of an Instagram post or reel.     Uses Playwright if available, othe", "file_type": "rationale", "source_file": "api/routers/preview.py", "source_location": "L134"}, {"id": "preview_rationale_171", "label": "Get preview of a YouTube video.      Uses official YouTube thumbnail API (fast,", "file_type": "rationale", "source_file": "api/routers/preview.py", "source_location": "L171"}], "edges": [{"source": "preview", "target": "fastapi", "relation": "imports_from", "confidence": "EXTRACTED", "source_file": "api/routers/preview.py", "source_location": "L2", "weight": 1.0}, {"source": "preview", "target": "fastapi_responses", "relation": "imports_from", "confidence": "EXTRACTED", "source_file": "api/routers/preview.py", "source_location": "L3", "weight": 1.0}, {"source": "preview", "target": "logging", "relation": "imports", "confidence": "EXTRACTED", "source_file": "api/routers/preview.py", "source_location": "L4", "weight": 1.0}, {"source": "preview", "target": "api_services_screenshot_service", "relation": "imports_from", "confidence": "EXTRACTED", "source_file": "api/routers/preview.py", "source_location": "L6", "weight": 1.0}, {"source": "preview", "target": "preview_preview_status", "relation": "contains", "confidence": "EXTRACTED", "source_file": "api/routers/preview.py", "source_location": "L19", "weight": 1.0}, {"source": "preview", "target": "preview_get_screenshot", "relation": "contains", "confidence": "EXTRACTED", "source_file": "api/routers/preview.py", "source_location": "L29", "weight": 1.0}, {"source": "preview", "target": "preview_get_link_preview_endpoint", "relation": "contains", "confidence": "EXTRACTED", "source_file": "api/routers/preview.py", "source_location": "L92", "weight": 1.0}, {"source": "preview", "target": "preview_get_instagram_preview", "relation": "contains", "confidence": "EXTRACTED", "source_file": "api/routers/preview.py", "source_location": "L131", "weight": 1.0}, {"source": "preview", "target": "preview_get_youtube_preview", "relation": "contains", "confidence": "EXTRACTED", "source_file": "api/routers/preview.py", "source_location": "L168", "weight": 1.0}, {"source": "preview_rationale_1", "target": "preview", "relation": "rationale_for", "confidence": "EXTRACTED", "source_file": "api/routers/preview.py", "source_location": "L1", "weight": 1.0}, {"source": "preview_rationale_20", "target": "preview_preview_status", "relation": "rationale_for", "confidence": "EXTRACTED", "source_file": "api/routers/preview.py", "source_location": "L20", "weight": 1.0}, {"source": "preview_rationale_35", "target": "preview_get_screenshot", "relation": "rationale_for", "confidence": "EXTRACTED", "source_file": "api/routers/preview.py", "source_location": "L35", "weight": 1.0}, {"source": "preview_rationale_95", "target": "preview_get_link_preview_endpoint", "relation": "rationale_for", "confidence": "EXTRACTED", "source_file": "api/routers/preview.py", "source_location": "L95", "weight": 1.0}, {"source": "preview_rationale_134", "target": "preview_get_instagram_preview", "relation": "rationale_for", "confidence": "EXTRACTED", "source_file": "api/routers/preview.py", "source_location": "L134", "weight": 1.0}, {"source": "preview_rationale_171", "target": "preview_get_youtube_preview", "relation": "rationale_for", "confidence": "EXTRACTED", "source_file": "api/routers/preview.py", "source_location": "L171", "weight": 1.0}]}