{"nodes": [{"id": "db_service", "label": "db_service.py", "file_type": "code", "source_file": "api/services/db_service.py", "source_location": "L1"}, {"id": "db_service_rationale_1", "label": "Backward compatibility \u2014 all functions moved to api.services.db/ modules.", "file_type": "rationale", "source_file": "api/services/db_service.py", "source_location": "L1"}], "edges": [{"source": "db_service", "target": "api_services_db", "relation": "imports_from", "confidence": "EXTRACTED", "source_file": "api/services/db_service.py", "source_location": "L2", "weight": 1.0}, {"source": "db_service", "target": "api_services_db", "relation": "imports_from", "confidence": "EXTRACTED", "source_file": "api/services/db_service.py", "source_location": "L3", "weight": 1.0}, {"source": "db_service_rationale_1", "target": "db_service", "relation": "rationale_for", "confidence": "EXTRACTED", "source_file": "api/services/db_service.py", "source_location": "L1", "weight": 1.0}]}