{"nodes": [{"id": "test_audit_dm_agent", "label": "test_audit_dm_agent.py", "file_type": "code", "source_file": "tests/audit/test_audit_dm_agent.py", "source_location": "L1"}, {"id": "test_audit_dm_agent_testauditdmagent", "label": "TestAuditDMAgent", "file_type": "code", "source_file": "tests/audit/test_audit_dm_agent.py", "source_location": "L6"}, {"id": "test_audit_dm_agent_testauditdmagent_test_import", "label": ".test_import()", "file_type": "code", "source_file": "tests/audit/test_audit_dm_agent.py", "source_location": "L7"}, {"id": "test_audit_dm_agent_testauditdmagent_test_agent_config", "label": ".test_agent_config()", "file_type": "code", "source_file": "tests/audit/test_audit_dm_agent.py", "source_location": "L18"}, {"id": "test_audit_dm_agent_testauditdmagent_test_happy_path_apply_voseo", "label": ".test_happy_path_apply_voseo()", "file_type": "code", "source_file": "tests/audit/test_audit_dm_agent.py", "source_location": "L25"}, {"id": "test_audit_dm_agent_testauditdmagent_test_edge_case_dm_response", "label": ".test_edge_case_dm_response()", "file_type": "code", "source_file": "tests/audit/test_audit_dm_agent.py", "source_location": "L29"}, {"id": "test_audit_dm_agent_testauditdmagent_test_error_handling_has_methods", "label": ".test_error_handling_has_methods()", "file_type": "code", "source_file": "tests/audit/test_audit_dm_agent.py", "source_location": "L37"}, {"id": "test_audit_dm_agent_rationale_1", "label": "Audit tests for core/dm_agent_v2.py", "file_type": "rationale", "source_file": "tests/audit/test_audit_dm_agent.py", "source_location": "L1"}], "edges": [{"source": "test_audit_dm_agent", "target": "core_dm_agent_v2", "relation": "imports_from", "confidence": "EXTRACTED", "source_file": "tests/audit/test_audit_dm_agent.py", "source_location": "L3", "weight": 1.0}, {"source": "test_audit_dm_agent", "target": "test_audit_dm_agent_testauditdmagent", "relation": "contains", "confidence": "EXTRACTED", "source_file": "tests/audit/test_audit_dm_agent.py", "source_location": "L6", "weight": 1.0}, {"source": "test_audit_dm_agent_testauditdmagent", "target": "test_audit_dm_agent_testauditdmagent_test_import", "relation": "method", "confidence": "EXTRACTED", "source_file": "tests/audit/test_audit_dm_agent.py", "source_location": "L7", "weight": 1.0}, {"source": "test_audit_dm_agent_testauditdmagent", "target": "test_audit_dm_agent_testauditdmagent_test_agent_config", "relation": "method", "confidence": "EXTRACTED", "source_file": "tests/audit/test_audit_dm_agent.py", "source_location": "L18", "weight": 1.0}, {"source": "test_audit_dm_agent_testauditdmagent", "target": "test_audit_dm_agent_testauditdmagent_test_happy_path_apply_voseo", "relation": "method", "confidence": "EXTRACTED", "source_file": "tests/audit/test_audit_dm_agent.py", "source_location": "L25", "weight": 1.0}, {"source": "test_audit_dm_agent_testauditdmagent", "target": "test_audit_dm_agent_testauditdmagent_test_edge_case_dm_response", "relation": "method", "confidence": "EXTRACTED", "source_file": "tests/audit/test_audit_dm_agent.py", "source_location": "L29", "weight": 1.0}, {"source": "test_audit_dm_agent_testauditdmagent", "target": "test_audit_dm_agent_testauditdmagent_test_error_handling_has_methods", "relation": "method", "confidence": "EXTRACTED", "source_file": "tests/audit/test_audit_dm_agent.py", "source_location": "L37", "weight": 1.0}, {"source": "test_audit_dm_agent_rationale_1", "target": "test_audit_dm_agent", "relation": "rationale_for", "confidence": "EXTRACTED", "source_file": "tests/audit/test_audit_dm_agent.py", "source_location": "L1", "weight": 1.0}]}