{"nodes": [{"id": "instagram_scraper", "label": "instagram_scraper.py", "file_type": "code", "source_file": "ingestion/instagram_scraper.py", "source_location": "L1"}, {"id": "instagram_scraper_instagramscrapererror", "label": "InstagramScraperError", "file_type": "code", "source_file": "ingestion/instagram_scraper.py", "source_location": "L30"}, {"id": "exception", "label": "Exception", "file_type": "code", "source_file": "", "source_location": ""}, {"id": "instagram_scraper_ratelimiterror", "label": "RateLimitError", "file_type": "code", "source_file": "ingestion/instagram_scraper.py", "source_location": "L35"}, {"id": "instagram_scraper_authenticationerror", "label": "AuthenticationError", "file_type": "code", "source_file": "ingestion/instagram_scraper.py", "source_location": "L40"}, {"id": "instagram_scraper_circuitbreakeropenerror", "label": "CircuitBreakerOpenError", "file_type": "code", "source_file": "ingestion/instagram_scraper.py", "source_location": "L45"}, {"id": "instagram_scraper_circuitbreakerlistener", "label": "CircuitBreakerListener", "file_type": "code", "source_file": "ingestion/instagram_scraper.py", "source_location": "L61"}, {"id": "instagram_scraper_circuitbreakerlistener_init", "label": ".__init__()", "file_type": "code", "source_file": "ingestion/instagram_scraper.py", "source_location": "L64"}, {"id": "instagram_scraper_circuitbreakerlistener_state_change", "label": ".state_change()", "file_type": "code", "source_file": "ingestion/instagram_scraper.py", "source_location": "L67"}, {"id": "instagram_scraper_circuitbreakerlistener_failure", "label": ".failure()", "file_type": "code", "source_file": "ingestion/instagram_scraper.py", "source_location": "L84"}, {"id": "instagram_scraper_circuitbreakerlistener_success", "label": ".success()", "file_type": "code", "source_file": "ingestion/instagram_scraper.py", "source_location": "L90"}, {"id": "instagram_scraper_instagrampost", "label": "InstagramPost", "file_type": "code", "source_file": "ingestion/instagram_scraper.py", "source_location": "L122"}, {"id": "instagram_scraper_has_content", "label": "has_content()", "file_type": "code", "source_file": "ingestion/instagram_scraper.py", "source_location": "L138"}, {"id": "instagram_scraper_metagraphapiscraper", "label": "MetaGraphAPIScraper", "file_type": "code", "source_file": "ingestion/instagram_scraper.py", "source_location": "L148"}, {"id": "instagram_scraper_metagraphapiscraper_init", "label": ".__init__()", "file_type": "code", "source_file": "ingestion/instagram_scraper.py", "source_location": "L158"}, {"id": "instagram_scraper_metagraphapiscraper_get_posts", "label": ".get_posts()", "file_type": "code", "source_file": "ingestion/instagram_scraper.py", "source_location": "L167"}, {"id": "instagram_scraper_metagraphapiscraper_fetch_posts_with_circuit_breaker", "label": "._fetch_posts_with_circuit_breaker()", "file_type": "code", "source_file": "ingestion/instagram_scraper.py", "source_location": "L208"}, {"id": "instagram_scraper_metagraphapiscraper_fetch_media_page", "label": "._fetch_media_page()", "file_type": "code", "source_file": "ingestion/instagram_scraper.py", "source_location": "L219"}, {"id": "instagram_scraper_metagraphapiscraper_parse_post", "label": "._parse_post()", "file_type": "code", "source_file": "ingestion/instagram_scraper.py", "source_location": "L262"}, {"id": "instagram_scraper_map_media_type", "label": "_map_media_type()", "file_type": "code", "source_file": "ingestion/instagram_scraper.py", "source_location": "L281"}, {"id": "instagram_scraper_extract_hashtags", "label": "_extract_hashtags()", "file_type": "code", "source_file": "ingestion/instagram_scraper.py", "source_location": "L291"}, {"id": "instagram_scraper_extract_mentions", "label": "_extract_mentions()", "file_type": "code", "source_file": "ingestion/instagram_scraper.py", "source_location": "L295"}, {"id": "instagram_scraper_instaloaderscraper", "label": "InstaloaderScraper", "file_type": "code", "source_file": "ingestion/instagram_scraper.py", "source_location": "L304"}, {"id": "instagram_scraper_instaloaderscraper_init", "label": ".__init__()", "file_type": "code", "source_file": "ingestion/instagram_scraper.py", "source_location": "L314"}, {"id": "instagram_scraper_instaloaderscraper_get_loader", "label": "._get_loader()", "file_type": "code", "source_file": "ingestion/instagram_scraper.py", "source_location": "L324"}, {"id": "instagram_scraper_instaloaderscraper_get_posts", "label": ".get_posts()", "file_type": "code", "source_file": "ingestion/instagram_scraper.py", "source_location": "L361"}, {"id": "instagram_scraper_instaloaderscraper_fetch_posts_internal", "label": "._fetch_posts_internal()", "file_type": "code", "source_file": "ingestion/instagram_scraper.py", "source_location": "L395"}, {"id": "instagram_scraper_get_post_type", "label": "_get_post_type()", "file_type": "code", "source_file": "ingestion/instagram_scraper.py", "source_location": "L465"}, {"id": "instagram_scraper_manualjsonscraper", "label": "ManualJSONScraper", "file_type": "code", "source_file": "ingestion/instagram_scraper.py", "source_location": "L480"}, {"id": "instagram_scraper_manualjsonscraper_parse_instagram_export", "label": ".parse_instagram_export()", "file_type": "code", "source_file": "ingestion/instagram_scraper.py", "source_location": "L492"}, {"id": "instagram_scraper_manualjsonscraper_parse_simple_json", "label": ".parse_simple_json()", "file_type": "code", "source_file": "ingestion/instagram_scraper.py", "source_location": "L529"}, {"id": "instagram_scraper_manualjsonscraper_parse_export_item", "label": "._parse_export_item()", "file_type": "code", "source_file": "ingestion/instagram_scraper.py", "source_location": "L573"}, {"id": "instagram_scraper_guess_type", "label": "_guess_type()", "file_type": "code", "source_file": "ingestion/instagram_scraper.py", "source_location": "L613"}, {"id": "instagram_scraper_get_instagram_scraper", "label": "get_instagram_scraper()", "file_type": "code", "source_file": "ingestion/instagram_scraper.py", "source_location": "L636"}, {"id": "instagram_scraper_rationale_1", "label": "Instagram Scraper - Obtiene posts y captions del creador. Fase 1 - Magic Slice", "file_type": "rationale", "source_file": "ingestion/instagram_scraper.py", "source_location": "L1"}, {"id": "instagram_scraper_rationale_31", "label": "Error base para el scraper.", "file_type": "rationale", "source_file": "ingestion/instagram_scraper.py", "source_location": "L31"}, {"id": "instagram_scraper_rationale_41", "label": "Error de autenticacion.", "file_type": "rationale", "source_file": "ingestion/instagram_scraper.py", "source_location": "L41"}, {"id": "instagram_scraper_rationale_46", "label": "Raised when circuit breaker is open and rejecting requests.", "file_type": "rationale", "source_file": "ingestion/instagram_scraper.py", "source_location": "L46"}, {"id": "instagram_scraper_rationale_62", "label": "Listener to log circuit breaker state changes.", "file_type": "rationale", "source_file": "ingestion/instagram_scraper.py", "source_location": "L62"}, {"id": "instagram_scraper_rationale_68", "label": "Log when circuit state changes.", "file_type": "rationale", "source_file": "ingestion/instagram_scraper.py", "source_location": "L68"}, {"id": "instagram_scraper_rationale_85", "label": "Log failures tracked by circuit breaker.", "file_type": "rationale", "source_file": "ingestion/instagram_scraper.py", "source_location": "L85"}, {"id": "instagram_scraper_rationale_91", "label": "Log successful calls (resets failure count).", "file_type": "rationale", "source_file": "ingestion/instagram_scraper.py", "source_location": "L91"}, {"id": "instagram_scraper_rationale_123", "label": "Representa un post de Instagram.", "file_type": "rationale", "source_file": "ingestion/instagram_scraper.py", "source_location": "L123"}, {"id": "instagram_scraper_rationale_139", "label": "Verifica si el post tiene contenido util para indexar.", "file_type": "rationale", "source_file": "ingestion/instagram_scraper.py", "source_location": "L139"}, {"id": "instagram_scraper_rationale_149", "label": "Scraper usando Meta Graph API oficial.     Requiere: Instagram Business/Creator", "file_type": "rationale", "source_file": "ingestion/instagram_scraper.py", "source_location": "L149"}, {"id": "instagram_scraper_rationale_159", "label": "Args:             access_token: Token de acceso de Meta (largo plazo preferido)", "file_type": "rationale", "source_file": "ingestion/instagram_scraper.py", "source_location": "L159"}, {"id": "instagram_scraper_rationale_170", "label": "Obtiene posts usando la Graph API.          Args:             limit: Numero maxi", "file_type": "rationale", "source_file": "ingestion/instagram_scraper.py", "source_location": "L170"}, {"id": "instagram_scraper_rationale_209", "label": "Fetch posts from Meta Graph API with circuit breaker protection.          This m", "file_type": "rationale", "source_file": "ingestion/instagram_scraper.py", "source_location": "L209"}, {"id": "instagram_scraper_rationale_220", "label": "Actual HTTP request to fetch media from Instagram API.          Separated for ci", "file_type": "rationale", "source_file": "ingestion/instagram_scraper.py", "source_location": "L220"}, {"id": "instagram_scraper_rationale_263", "label": "Parsea respuesta de la API a InstagramPost.", "file_type": "rationale", "source_file": "ingestion/instagram_scraper.py", "source_location": "L263"}, {"id": "instagram_scraper_rationale_305", "label": "Scraper usando Instaloader (no oficial).      ADVERTENCIA: Puede ser bloqueado p", "file_type": "rationale", "source_file": "ingestion/instagram_scraper.py", "source_location": "L305"}, {"id": "instagram_scraper_rationale_315", "label": "Args:             username: Usuario de Instagram (opcional, mejora limites)", "file_type": "rationale", "source_file": "ingestion/instagram_scraper.py", "source_location": "L315"}, {"id": "instagram_scraper_rationale_325", "label": "Inicializa Instaloader de forma lazy con configuraci\u00f3n anti-rate-limit.", "file_type": "rationale", "source_file": "ingestion/instagram_scraper.py", "source_location": "L325"}, {"id": "instagram_scraper_rationale_368", "label": "Obtiene posts de un perfil usando Instaloader.          Args:             target", "file_type": "rationale", "source_file": "ingestion/instagram_scraper.py", "source_location": "L368"}, {"id": "instagram_scraper_rationale_402", "label": "Internal method to fetch posts - wrapped by circuit breaker.", "file_type": "rationale", "source_file": "ingestion/instagram_scraper.py", "source_location": "L402"}, {"id": "instagram_scraper_rationale_481", "label": "Procesa datos exportados manualmente por el creador.      El creador puede:", "file_type": "rationale", "source_file": "ingestion/instagram_scraper.py", "source_location": "L481"}, {"id": "instagram_scraper_rationale_493", "label": "Parsea el archivo JSON de exportacion de Instagram.          Args:             j", "file_type": "rationale", "source_file": "ingestion/instagram_scraper.py", "source_location": "L493"}, {"id": "instagram_scraper_rationale_530", "label": "Parsea un JSON simple con estructura basica.          Formato esperado:", "file_type": "rationale", "source_file": "ingestion/instagram_scraper.py", "source_location": "L530"}, {"id": "instagram_scraper_rationale_574", "label": "Parsea un item del export oficial de Instagram.", "file_type": "rationale", "source_file": "ingestion/instagram_scraper.py", "source_location": "L574"}, {"id": "instagram_scraper_rationale_639", "label": "Factory para obtener el scraper apropiado.      Args:         method: Metodo a u", "file_type": "rationale", "source_file": "ingestion/instagram_scraper.py", "source_location": "L639"}], "edges": [{"source": "instagram_scraper", "target": "json", "relation": "imports", "confidence": "EXTRACTED", "source_file": "ingestion/instagram_scraper.py", "source_location": "L11", "weight": 1.0}, {"source": "instagram_scraper", "target": "logging", "relation": "imports", "confidence": "EXTRACTED", "source_file": "ingestion/instagram_scraper.py", "source_location": "L12", "weight": 1.0}, {"source": "instagram_scraper", "target": "os", "relation": "imports", "confidence": "EXTRACTED", "source_file": "ingestion/instagram_scraper.py", "source_location": "L13", "weight": 1.0}, {"source": "instagram_scraper", "target": "re", "relation": "imports", "confidence": "EXTRACTED", "source_file": "ingestion/instagram_scraper.py", "source_location": "L14", "weight": 1.0}, {"source": "instagram_scraper", "target": "dataclasses", "relation": "imports_from", "confidence": "EXTRACTED", "source_file": "ingestion/instagram_scraper.py", "source_location": "L15", "weight": 1.0}, {"source": "instagram_scraper", "target": "datetime", "relation": "imports_from", "confidence": "EXTRACTED", "source_file": "ingestion/instagram_scraper.py", "source_location": "L16", "weight": 1.0}, {"source": "instagram_scraper", "target": "pathlib", "relation": "imports_from", "confidence": "EXTRACTED", "source_file": "ingestion/instagram_scraper.py", "source_location": "L17", "weight": 1.0}, {"source": "instagram_scraper", "target": "typing", "relation": "imports_from", "confidence": "EXTRACTED", "source_file": "ingestion/instagram_scraper.py", "source_location": "L18", "weight": 1.0}, {"source": "instagram_scraper", "target": "pybreaker", "relation": "imports", "confidence": "EXTRACTED", "source_file": "ingestion/instagram_scraper.py", "source_location": "L20", "weight": 1.0}, {"source": "instagram_scraper", "target": "instagram_scraper_instagramscrapererror", "relation": "contains", "confidence": "EXTRACTED", "source_file": "ingestion/instagram_scraper.py", "source_location": "L30", "weight": 1.0}, {"source": "instagram_scraper_instagramscrapererror", "target": "exception", "relation": "inherits", "confidence": "EXTRACTED", "source_file": "ingestion/instagram_scraper.py", "source_location": "L30", "weight": 1.0}, {"source": "instagram_scraper", "target": "instagram_scraper_ratelimiterror", "relation": "contains", "confidence": "EXTRACTED", "source_file": "ingestion/instagram_scraper.py", "source_location": "L35", "weight": 1.0}, {"source": "instagram_scraper_ratelimiterror", "target": "instagram_scraper_instagramscrapererror", "relation": "inherits", "confidence": "EXTRACTED", "source_file": "ingestion/instagram_scraper.py", "source_location": "L35", "weight": 1.0}, {"source": "instagram_scraper", "target": "instagram_scraper_authenticationerror", "relation": "contains", "confidence": "EXTRACTED", "source_file": "ingestion/instagram_scraper.py", "source_location": "L40", "weight": 1.0}, {"source": "instagram_scraper_authenticationerror", "target": "instagram_scraper_instagramscrapererror", "relation": "inherits", "confidence": "EXTRACTED", "source_file": "ingestion/instagram_scraper.py", "source_location": "L40", "weight": 1.0}, {"source": "instagram_scraper", "target": "instagram_scraper_circuitbreakeropenerror", "relation": "contains", "confidence": "EXTRACTED", "source_file": "ingestion/instagram_scraper.py", "source_location": "L45", "weight": 1.0}, {"source": "instagram_scraper_circuitbreakeropenerror", "target": "instagram_scraper_instagramscrapererror", "relation": "inherits", "confidence": "EXTRACTED", "source_file": "ingestion/instagram_scraper.py", "source_location": "L45", "weight": 1.0}, {"source": "instagram_scraper", "target": "instagram_scraper_circuitbreakerlistener", "relation": "contains", "confidence": "EXTRACTED", "source_file": "ingestion/instagram_scraper.py", "source_location": "L61", "weight": 1.0}, {"source": "instagram_scraper_circuitbreakerlistener", "target": "instagram_scraper_circuitbreakerlistener_init", "relation": "method", "confidence": "EXTRACTED", "source_file": "ingestion/instagram_scraper.py", "source_location": "L64", "weight": 1.0}, {"source": "instagram_scraper_circuitbreakerlistener", "target": "instagram_scraper_circuitbreakerlistener_state_change", "relation": "method", "confidence": "EXTRACTED", "source_file": "ingestion/instagram_scraper.py", "source_location": "L67", "weight": 1.0}, {"source": "instagram_scraper_circuitbreakerlistener", "target": "instagram_scraper_circuitbreakerlistener_failure", "relation": "method", "confidence": "EXTRACTED", "source_file": "ingestion/instagram_scraper.py", "source_location": "L84", "weight": 1.0}, {"source": "instagram_scraper_circuitbreakerlistener", "target": "instagram_scraper_circuitbreakerlistener_success", "relation": "method", "confidence": "EXTRACTED", "source_file": "ingestion/instagram_scraper.py", "source_location": "L90", "weight": 1.0}, {"source": "instagram_scraper", "target": "instagram_scraper_instagrampost", "relation": "contains", "confidence": "EXTRACTED", "source_file": "ingestion/instagram_scraper.py", "source_location": "L122", "weight": 1.0}, {"source": "instagram_scraper", "target": "instagram_scraper_has_content", "relation": "contains", "confidence": "EXTRACTED", "source_file": "ingestion/instagram_scraper.py", "source_location": "L138", "weight": 1.0}, {"source": "instagram_scraper", "target": "instagram_scraper_metagraphapiscraper", "relation": "contains", "confidence": "EXTRACTED", "source_file": "ingestion/instagram_scraper.py", "source_location": "L148", "weight": 1.0}, {"source": "instagram_scraper_metagraphapiscraper", "target": "instagram_scraper_metagraphapiscraper_init", "relation": "method", "confidence": "EXTRACTED", "source_file": "ingestion/instagram_scraper.py", "source_location": "L158", "weight": 1.0}, {"source": "instagram_scraper_metagraphapiscraper", "target": "instagram_scraper_metagraphapiscraper_get_posts", "relation": "method", "confidence": "EXTRACTED", "source_file": "ingestion/instagram_scraper.py", "source_location": "L167", "weight": 1.0}, {"source": "instagram_scraper_metagraphapiscraper", "target": "instagram_scraper_metagraphapiscraper_fetch_posts_with_circuit_breaker", "relation": "method", "confidence": "EXTRACTED", "source_file": "ingestion/instagram_scraper.py", "source_location": "L208", "weight": 1.0}, {"source": "instagram_scraper_metagraphapiscraper", "target": "instagram_scraper_metagraphapiscraper_fetch_media_page", "relation": "method", "confidence": "EXTRACTED", "source_file": "ingestion/instagram_scraper.py", "source_location": "L219", "weight": 1.0}, {"source": "instagram_scraper_metagraphapiscraper", "target": "instagram_scraper_metagraphapiscraper_parse_post", "relation": "method", "confidence": "EXTRACTED", "source_file": "ingestion/instagram_scraper.py", "source_location": "L262", "weight": 1.0}, {"source": "instagram_scraper", "target": "instagram_scraper_map_media_type", "relation": "contains", "confidence": "EXTRACTED", "source_file": "ingestion/instagram_scraper.py", "source_location": "L281", "weight": 1.0}, {"source": "instagram_scraper", "target": "instagram_scraper_extract_hashtags", "relation": "contains", "confidence": "EXTRACTED", "source_file": "ingestion/instagram_scraper.py", "source_location": "L291", "weight": 1.0}, {"source": "instagram_scraper", "target": "instagram_scraper_extract_mentions", "relation": "contains", "confidence": "EXTRACTED", "source_file": "ingestion/instagram_scraper.py", "source_location": "L295", "weight": 1.0}, {"source": "instagram_scraper", "target": "instagram_scraper_instaloaderscraper", "relation": "contains", "confidence": "EXTRACTED", "source_file": "ingestion/instagram_scraper.py", "source_location": "L304", "weight": 1.0}, {"source": "instagram_scraper_instaloaderscraper", "target": "instagram_scraper_instaloaderscraper_init", "relation": "method", "confidence": "EXTRACTED", "source_file": "ingestion/instagram_scraper.py", "source_location": "L314", "weight": 1.0}, {"source": "instagram_scraper_instaloaderscraper", "target": "instagram_scraper_instaloaderscraper_get_loader", "relation": "method", "confidence": "EXTRACTED", "source_file": "ingestion/instagram_scraper.py", "source_location": "L324", "weight": 1.0}, {"source": "instagram_scraper_instaloaderscraper", "target": "instagram_scraper_instaloaderscraper_get_posts", "relation": "method", "confidence": "EXTRACTED", "source_file": "ingestion/instagram_scraper.py", "source_location": "L361", "weight": 1.0}, {"source": "instagram_scraper_instaloaderscraper", "target": "instagram_scraper_instaloaderscraper_fetch_posts_internal", "relation": "method", "confidence": "EXTRACTED", "source_file": "ingestion/instagram_scraper.py", "source_location": "L395", "weight": 1.0}, {"source": "instagram_scraper", "target": "instagram_scraper_get_post_type", "relation": "contains", "confidence": "EXTRACTED", "source_file": "ingestion/instagram_scraper.py", "source_location": "L465", "weight": 1.0}, {"source": "instagram_scraper", "target": "instagram_scraper_manualjsonscraper", "relation": "contains", "confidence": "EXTRACTED", "source_file": "ingestion/instagram_scraper.py", "source_location": "L480", "weight": 1.0}, {"source": "instagram_scraper_manualjsonscraper", "target": "instagram_scraper_manualjsonscraper_parse_instagram_export", "relation": "method", "confidence": "EXTRACTED", "source_file": "ingestion/instagram_scraper.py", "source_location": "L492", "weight": 1.0}, {"source": "instagram_scraper_manualjsonscraper", "target": "instagram_scraper_manualjsonscraper_parse_simple_json", "relation": "method", "confidence": "EXTRACTED", "source_file": "ingestion/instagram_scraper.py", "source_location": "L529", "weight": 1.0}, {"source": "instagram_scraper_manualjsonscraper", "target": "instagram_scraper_manualjsonscraper_parse_export_item", "relation": "method", "confidence": "EXTRACTED", "source_file": "ingestion/instagram_scraper.py", "source_location": "L573", "weight": 1.0}, {"source": "instagram_scraper", "target": "instagram_scraper_guess_type", "relation": "contains", "confidence": "EXTRACTED", "source_file": "ingestion/instagram_scraper.py", "source_location": "L613", "weight": 1.0}, {"source": "instagram_scraper", "target": "instagram_scraper_extract_hashtags", "relation": "contains", "confidence": "EXTRACTED", "source_file": "ingestion/instagram_scraper.py", "source_location": "L623", "weight": 1.0}, {"source": "instagram_scraper", "target": "instagram_scraper_extract_mentions", "relation": "contains", "confidence": "EXTRACTED", "source_file": "ingestion/instagram_scraper.py", "source_location": "L627", "weight": 1.0}, {"source": "instagram_scraper", "target": "instagram_scraper_get_instagram_scraper", "relation": "contains", "confidence": "EXTRACTED", "source_file": "ingestion/instagram_scraper.py", "source_location": "L636", "weight": 1.0}, {"source": "instagram_scraper_metagraphapiscraper_get_posts", "target": "instagram_scraper_metagraphapiscraper_fetch_posts_with_circuit_breaker", "relation": "calls", "confidence": "EXTRACTED", "source_file": "ingestion/instagram_scraper.py", "source_location": "L187", "weight": 1.0}, {"source": "instagram_scraper_metagraphapiscraper_get_posts", "target": "instagram_scraper_circuitbreakeropenerror", "relation": "calls", "confidence": "EXTRACTED", "source_file": "ingestion/instagram_scraper.py", "source_location": "L189", "weight": 1.0}, {"source": "instagram_scraper_metagraphapiscraper_get_posts", "target": "instagram_scraper_metagraphapiscraper_parse_post", "relation": "calls", "confidence": "EXTRACTED", "source_file": "ingestion/instagram_scraper.py", "source_location": "L196", "weight": 1.0}, {"source": "instagram_scraper_metagraphapiscraper_fetch_posts_with_circuit_breaker", "target": "instagram_scraper_metagraphapiscraper_fetch_media_page", "relation": "calls", "confidence": "EXTRACTED", "source_file": "ingestion/instagram_scraper.py", "source_location": "L217", "weight": 1.0}, {"source": "instagram_scraper_metagraphapiscraper_fetch_media_page", "target": "instagram_scraper_ratelimiterror", "relation": "calls", "confidence": "EXTRACTED", "source_file": "ingestion/instagram_scraper.py", "source_location": "L239", "weight": 1.0}, {"source": "instagram_scraper_metagraphapiscraper_fetch_media_page", "target": "instagram_scraper_authenticationerror", "relation": "calls", "confidence": "EXTRACTED", "source_file": "ingestion/instagram_scraper.py", "source_location": "L242", "weight": 1.0}, {"source": "instagram_scraper_metagraphapiscraper_fetch_media_page", "target": "instagram_scraper_instagramscrapererror", "relation": "calls", "confidence": "EXTRACTED", "source_file": "ingestion/instagram_scraper.py", "source_location": "L246", "weight": 1.0}, {"source": "instagram_scraper_metagraphapiscraper_parse_post", "target": "instagram_scraper_instagrampost", "relation": "calls", "confidence": "EXTRACTED", "source_file": "ingestion/instagram_scraper.py", "source_location": "L266", "weight": 1.0}, {"source": "instagram_scraper_metagraphapiscraper_parse_post", "target": "instagram_scraper_map_media_type", "relation": "calls", "confidence": "EXTRACTED", "source_file": "ingestion/instagram_scraper.py", "source_location": "L268", "weight": 1.0}, {"source": "instagram_scraper_metagraphapiscraper_parse_post", "target": "instagram_scraper_extract_hashtags", "relation": "calls", "confidence": "EXTRACTED", "source_file": "ingestion/instagram_scraper.py", "source_location": "L276", "weight": 1.0}, {"source": "instagram_scraper_metagraphapiscraper_parse_post", "target": "instagram_scraper_extract_mentions", "relation": "calls", "confidence": "EXTRACTED", "source_file": "ingestion/instagram_scraper.py", "source_location": "L277", "weight": 1.0}, {"source": "instagram_scraper_instaloaderscraper_get_loader", "target": "instagram_scraper_instagramscrapererror", "relation": "calls", "confidence": "EXTRACTED", "source_file": "ingestion/instagram_scraper.py", "source_location": "L355", "weight": 1.0}, {"source": "instagram_scraper_instaloaderscraper_get_posts", "target": "instagram_scraper_circuitbreakeropenerror", "relation": "calls", "confidence": "EXTRACTED", "source_file": "ingestion/instagram_scraper.py", "source_location": "L390", "weight": 1.0}, {"source": "instagram_scraper_instaloaderscraper_fetch_posts_internal", "target": "instagram_scraper_instaloaderscraper_get_loader", "relation": "calls", "confidence": "EXTRACTED", "source_file": "ingestion/instagram_scraper.py", "source_location": "L410", "weight": 1.0}, {"source": "instagram_scraper_instaloaderscraper_fetch_posts_internal", "target": "instagram_scraper_instaloaderscraper_get_posts", "relation": "calls", "confidence": "EXTRACTED", "source_file": "ingestion/instagram_scraper.py", "source_location": "L420", "weight": 1.0}, {"source": "instagram_scraper_instaloaderscraper_fetch_posts_internal", "target": "instagram_scraper_instagrampost", "relation": "calls", "confidence": "EXTRACTED", "source_file": "ingestion/instagram_scraper.py", "source_location": "L429", "weight": 1.0}, {"source": "instagram_scraper_instaloaderscraper_fetch_posts_internal", "target": "instagram_scraper_get_post_type", "relation": "calls", "confidence": "EXTRACTED", "source_file": "ingestion/instagram_scraper.py", "source_location": "L431", "weight": 1.0}, {"source": "instagram_scraper_instaloaderscraper_fetch_posts_internal", "target": "instagram_scraper_instagramscrapererror", "relation": "calls", "confidence": "EXTRACTED", "source_file": "ingestion/instagram_scraper.py", "source_location": "L455", "weight": 1.0}, {"source": "instagram_scraper_instaloaderscraper_fetch_posts_internal", "target": "instagram_scraper_ratelimiterror", "relation": "calls", "confidence": "EXTRACTED", "source_file": "ingestion/instagram_scraper.py", "source_location": "L458", "weight": 1.0}, {"source": "instagram_scraper_manualjsonscraper_parse_instagram_export", "target": "instagram_scraper_instagramscrapererror", "relation": "calls", "confidence": "EXTRACTED", "source_file": "ingestion/instagram_scraper.py", "source_location": "L504", "weight": 1.0}, {"source": "instagram_scraper_manualjsonscraper_parse_instagram_export", "target": "instagram_scraper_manualjsonscraper_parse_export_item", "relation": "calls", "confidence": "EXTRACTED", "source_file": "ingestion/instagram_scraper.py", "source_location": "L522", "weight": 1.0}, {"source": "instagram_scraper_manualjsonscraper_parse_simple_json", "target": "instagram_scraper_instagrampost", "relation": "calls", "confidence": "EXTRACTED", "source_file": "ingestion/instagram_scraper.py", "source_location": "L550", "weight": 1.0}, {"source": "instagram_scraper_manualjsonscraper_parse_simple_json", "target": "instagram_scraper_extract_hashtags", "relation": "calls", "confidence": "EXTRACTED", "source_file": "ingestion/instagram_scraper.py", "source_location": "L560", "weight": 1.0}, {"source": "instagram_scraper_manualjsonscraper_parse_simple_json", "target": "instagram_scraper_extract_mentions", "relation": "calls", "confidence": "EXTRACTED", "source_file": "ingestion/instagram_scraper.py", "source_location": "L561", "weight": 1.0}, {"source": "instagram_scraper_manualjsonscraper_parse_export_item", "target": "instagram_scraper_instagrampost", "relation": "calls", "confidence": "EXTRACTED", "source_file": "ingestion/instagram_scraper.py", "source_location": "L598", "weight": 1.0}, {"source": "instagram_scraper_manualjsonscraper_parse_export_item", "target": "instagram_scraper_guess_type", "relation": "calls", "confidence": "EXTRACTED", "source_file": "ingestion/instagram_scraper.py", "source_location": "L600", "weight": 1.0}, {"source": "instagram_scraper_manualjsonscraper_parse_export_item", "target": "instagram_scraper_extract_hashtags", "relation": "calls", "confidence": "EXTRACTED", "source_file": "ingestion/instagram_scraper.py", "source_location": "L604", "weight": 1.0}, {"source": "instagram_scraper_manualjsonscraper_parse_export_item", "target": "instagram_scraper_extract_mentions", "relation": "calls", "confidence": "EXTRACTED", "source_file": "ingestion/instagram_scraper.py", "source_location": "L605", "weight": 1.0}, {"source": "instagram_scraper_get_instagram_scraper", "target": "instagram_scraper_metagraphapiscraper", "relation": "calls", "confidence": "EXTRACTED", "source_file": "ingestion/instagram_scraper.py", "source_location": "L668", "weight": 1.0}, {"source": "instagram_scraper_get_instagram_scraper", "target": "instagram_scraper_instaloaderscraper", "relation": "calls", "confidence": "EXTRACTED", "source_file": "ingestion/instagram_scraper.py", "source_location": "L673", "weight": 1.0}, {"source": "instagram_scraper_get_instagram_scraper", "target": "instagram_scraper_manualjsonscraper", "relation": "calls", "confidence": "EXTRACTED", "source_file": "ingestion/instagram_scraper.py", "source_location": "L675", "weight": 1.0}, {"source": "instagram_scraper_rationale_1", "target": "instagram_scraper", "relation": "rationale_for", "confidence": "EXTRACTED", "source_file": "ingestion/instagram_scraper.py", "source_location": "L1", "weight": 1.0}, {"source": "instagram_scraper_rationale_31", "target": "instagram_scraper_instagramscrapererror", "relation": "rationale_for", "confidence": "EXTRACTED", "source_file": "ingestion/instagram_scraper.py", "source_location": "L31", "weight": 1.0}, {"source": "instagram_scraper_rationale_41", "target": "instagram_scraper_authenticationerror", "relation": "rationale_for", "confidence": "EXTRACTED", "source_file": "ingestion/instagram_scraper.py", "source_location": "L41", "weight": 1.0}, {"source": "instagram_scraper_rationale_46", "target": "instagram_scraper_circuitbreakeropenerror", "relation": "rationale_for", "confidence": "EXTRACTED", "source_file": "ingestion/instagram_scraper.py", "source_location": "L46", "weight": 1.0}, {"source": "instagram_scraper_rationale_62", "target": "instagram_scraper_circuitbreakerlistener", "relation": "rationale_for", "confidence": "EXTRACTED", "source_file": "ingestion/instagram_scraper.py", "source_location": "L62", "weight": 1.0}, {"source": "instagram_scraper_rationale_68", "target": "instagram_scraper_circuitbreakerlistener_state_change", "relation": "rationale_for", "confidence": "EXTRACTED", "source_file": "ingestion/instagram_scraper.py", "source_location": "L68", "weight": 1.0}, {"source": "instagram_scraper_rationale_85", "target": "instagram_scraper_circuitbreakerlistener_failure", "relation": "rationale_for", "confidence": "EXTRACTED", "source_file": "ingestion/instagram_scraper.py", "source_location": "L85", "weight": 1.0}, {"source": "instagram_scraper_rationale_91", "target": "instagram_scraper_circuitbreakerlistener_success", "relation": "rationale_for", "confidence": "EXTRACTED", "source_file": "ingestion/instagram_scraper.py", "source_location": "L91", "weight": 1.0}, {"source": "instagram_scraper_rationale_123", "target": "instagram_scraper_instagrampost", "relation": "rationale_for", "confidence": "EXTRACTED", "source_file": "ingestion/instagram_scraper.py", "source_location": "L123", "weight": 1.0}, {"source": "instagram_scraper_rationale_139", "target": "instagram_scraper_instagrampost_has_content", "relation": "rationale_for", "confidence": "EXTRACTED", "source_file": "ingestion/instagram_scraper.py", "source_location": "L139", "weight": 1.0}, {"source": "instagram_scraper_rationale_149", "target": "instagram_scraper_metagraphapiscraper", "relation": "rationale_for", "confidence": "EXTRACTED", "source_file": "ingestion/instagram_scraper.py", "source_location": "L149", "weight": 1.0}, {"source": "instagram_scraper_rationale_159", "target": "instagram_scraper_metagraphapiscraper_init", "relation": "rationale_for", "confidence": "EXTRACTED", "source_file": "ingestion/instagram_scraper.py", "source_location": "L159", "weight": 1.0}, {"source": "instagram_scraper_rationale_170", "target": "instagram_scraper_metagraphapiscraper_get_posts", "relation": "rationale_for", "confidence": "EXTRACTED", "source_file": "ingestion/instagram_scraper.py", "source_location": "L170", "weight": 1.0}, {"source": "instagram_scraper_rationale_209", "target": "instagram_scraper_metagraphapiscraper_fetch_posts_with_circuit_breaker", "relation": "rationale_for", "confidence": "EXTRACTED", "source_file": "ingestion/instagram_scraper.py", "source_location": "L209", "weight": 1.0}, {"source": "instagram_scraper_rationale_220", "target": "instagram_scraper_metagraphapiscraper_fetch_media_page", "relation": "rationale_for", "confidence": "EXTRACTED", "source_file": "ingestion/instagram_scraper.py", "source_location": "L220", "weight": 1.0}, {"source": "instagram_scraper_rationale_263", "target": "instagram_scraper_metagraphapiscraper_parse_post", "relation": "rationale_for", "confidence": "EXTRACTED", "source_file": "ingestion/instagram_scraper.py", "source_location": "L263", "weight": 1.0}, {"source": "instagram_scraper_rationale_305", "target": "instagram_scraper_instaloaderscraper", "relation": "rationale_for", "confidence": "EXTRACTED", "source_file": "ingestion/instagram_scraper.py", "source_location": "L305", "weight": 1.0}, {"source": "instagram_scraper_rationale_315", "target": "instagram_scraper_instaloaderscraper_init", "relation": "rationale_for", "confidence": "EXTRACTED", "source_file": "ingestion/instagram_scraper.py", "source_location": "L315", "weight": 1.0}, {"source": "instagram_scraper_rationale_325", "target": "instagram_scraper_instaloaderscraper_get_loader", "relation": "rationale_for", "confidence": "EXTRACTED", "source_file": "ingestion/instagram_scraper.py", "source_location": "L325", "weight": 1.0}, {"source": "instagram_scraper_rationale_368", "target": "instagram_scraper_instaloaderscraper_get_posts", "relation": "rationale_for", "confidence": "EXTRACTED", "source_file": "ingestion/instagram_scraper.py", "source_location": "L368", "weight": 1.0}, {"source": "instagram_scraper_rationale_402", "target": "instagram_scraper_instaloaderscraper_fetch_posts_internal", "relation": "rationale_for", "confidence": "EXTRACTED", "source_file": "ingestion/instagram_scraper.py", "source_location": "L402", "weight": 1.0}, {"source": "instagram_scraper_rationale_481", "target": "instagram_scraper_manualjsonscraper", "relation": "rationale_for", "confidence": "EXTRACTED", "source_file": "ingestion/instagram_scraper.py", "source_location": "L481", "weight": 1.0}, {"source": "instagram_scraper_rationale_493", "target": "instagram_scraper_manualjsonscraper_parse_instagram_export", "relation": "rationale_for", "confidence": "EXTRACTED", "source_file": "ingestion/instagram_scraper.py", "source_location": "L493", "weight": 1.0}, {"source": "instagram_scraper_rationale_530", "target": "instagram_scraper_manualjsonscraper_parse_simple_json", "relation": "rationale_for", "confidence": "EXTRACTED", "source_file": "ingestion/instagram_scraper.py", "source_location": "L530", "weight": 1.0}, {"source": "instagram_scraper_rationale_574", "target": "instagram_scraper_manualjsonscraper_parse_export_item", "relation": "rationale_for", "confidence": "EXTRACTED", "source_file": "ingestion/instagram_scraper.py", "source_location": "L574", "weight": 1.0}, {"source": "instagram_scraper_rationale_639", "target": "instagram_scraper_get_instagram_scraper", "relation": "rationale_for", "confidence": "EXTRACTED", "source_file": "ingestion/instagram_scraper.py", "source_location": "L639", "weight": 1.0}]}