{"nodes": [{"id": "test_contextual_prefix", "label": "test_contextual_prefix.py", "file_type": "code", "source_file": "tests/test_contextual_prefix.py", "source_location": "L1"}, {"id": "test_contextual_prefix_make_creator_data", "label": "_make_creator_data()", "file_type": "code", "source_file": "tests/test_contextual_prefix.py", "source_location": "L16"}, {"id": "test_contextual_prefix_testbuildcontextualprefix", "label": "TestBuildContextualPrefix", "file_type": "code", "source_file": "tests/test_contextual_prefix.py", "source_location": "L54"}, {"id": "test_contextual_prefix_testbuildcontextualprefix_setup_method", "label": ".setup_method()", "file_type": "code", "source_file": "tests/test_contextual_prefix.py", "source_location": "L57"}, {"id": "test_contextual_prefix_test_full_data_prefix", "label": "test_full_data_prefix()", "file_type": "code", "source_file": "tests/test_contextual_prefix.py", "source_location": "L63"}, {"id": "test_contextual_prefix_test_missing_specialties_uses_bio", "label": "test_missing_specialties_uses_bio()", "file_type": "code", "source_file": "tests/test_contextual_prefix.py", "source_location": "L78"}, {"id": "test_contextual_prefix_test_missing_all_knowledge_about", "label": "test_missing_all_knowledge_about()", "file_type": "code", "source_file": "tests/test_contextual_prefix.py", "source_location": "L90"}, {"id": "test_contextual_prefix_test_no_creator_returns_empty", "label": "test_no_creator_returns_empty()", "file_type": "code", "source_file": "tests/test_contextual_prefix.py", "source_location": "L100"}, {"id": "test_contextual_prefix_test_prefix_is_cached", "label": "test_prefix_is_cached()", "file_type": "code", "source_file": "tests/test_contextual_prefix.py", "source_location": "L113"}, {"id": "test_contextual_prefix_test_prefix_capped_at_500_chars", "label": "test_prefix_capped_at_500_chars()", "file_type": "code", "source_file": "tests/test_contextual_prefix.py", "source_location": "L124"}, {"id": "test_contextual_prefix_test_formal_style_mentioned", "label": "test_formal_style_mentioned()", "file_type": "code", "source_file": "tests/test_contextual_prefix.py", "source_location": "L137"}, {"id": "test_contextual_prefix_test_italian_dialect", "label": "test_italian_dialect()", "file_type": "code", "source_file": "tests/test_contextual_prefix.py", "source_location": "L147"}, {"id": "test_contextual_prefix_test_db_error_returns_empty", "label": "test_db_error_returns_empty()", "file_type": "code", "source_file": "tests/test_contextual_prefix.py", "source_location": "L167"}, {"id": "test_contextual_prefix_test_product_fallback_when_no_specialties", "label": "test_product_fallback_when_no_specialties()", "file_type": "code", "source_file": "tests/test_contextual_prefix.py", "source_location": "L174"}, {"id": "test_contextual_prefix_test_faq_fallback_when_only_name", "label": "test_faq_fallback_when_only_name()", "file_type": "code", "source_file": "tests/test_contextual_prefix.py", "source_location": "L195"}, {"id": "test_contextual_prefix_testgenerateembeddingwithcontext", "label": "TestGenerateEmbeddingWithContext", "file_type": "code", "source_file": "tests/test_contextual_prefix.py", "source_location": "L213"}, {"id": "test_contextual_prefix_testgenerateembeddingwithcontext_setup_method", "label": ".setup_method()", "file_type": "code", "source_file": "tests/test_contextual_prefix.py", "source_location": "L216"}, {"id": "test_contextual_prefix_test_prepends_prefix", "label": "test_prepends_prefix()", "file_type": "code", "source_file": "tests/test_contextual_prefix.py", "source_location": "L222"}, {"id": "test_contextual_prefix_test_empty_prefix_passes_text_only", "label": "test_empty_prefix_passes_text_only()", "file_type": "code", "source_file": "tests/test_contextual_prefix.py", "source_location": "L238"}, {"id": "test_contextual_prefix_test_batch_prepends_to_all", "label": "test_batch_prepends_to_all()", "file_type": "code", "source_file": "tests/test_contextual_prefix.py", "source_location": "L253"}, {"id": "test_contextual_prefix_testsearchqueriesnotprefixed", "label": "TestSearchQueriesNotPrefixed", "file_type": "code", "source_file": "tests/test_contextual_prefix.py", "source_location": "L269"}, {"id": "test_contextual_prefix_testsearchqueriesnotprefixed_test_semantic_search_uses_raw_embedding", "label": ".test_semantic_search_uses_raw_embedding()", "file_type": "code", "source_file": "tests/test_contextual_prefix.py", "source_location": "L272"}, {"id": "test_contextual_prefix_rationale_1", "label": "Tests for core/contextual_prefix.py \u2014 Universal Contextual Prefix for RAG.  Vali", "file_type": "rationale", "source_file": "tests/test_contextual_prefix.py", "source_location": "L1"}, {"id": "test_contextual_prefix_rationale_25", "label": "Build a mock CreatorData for testing.", "file_type": "rationale", "source_file": "tests/test_contextual_prefix.py", "source_location": "L25"}, {"id": "test_contextual_prefix_rationale_55", "label": "Test build_contextual_prefix() function.", "file_type": "rationale", "source_file": "tests/test_contextual_prefix.py", "source_location": "L55"}, {"id": "test_contextual_prefix_rationale_58", "label": "Clear prefix cache before each test.", "file_type": "rationale", "source_file": "tests/test_contextual_prefix.py", "source_location": "L58"}, {"id": "test_contextual_prefix_rationale_64", "label": "Prefix with complete data should contain name, handle, domain, location, languag", "file_type": "rationale", "source_file": "tests/test_contextual_prefix.py", "source_location": "L64"}, {"id": "test_contextual_prefix_rationale_79", "label": "When specialties are missing, falls back to bio first sentence.", "file_type": "rationale", "source_file": "tests/test_contextual_prefix.py", "source_location": "L79"}, {"id": "test_contextual_prefix_rationale_91", "label": "Prefix with no knowledge_about should still include name.", "file_type": "rationale", "source_file": "tests/test_contextual_prefix.py", "source_location": "L91"}, {"id": "test_contextual_prefix_rationale_101", "label": "Non-existent creator should return empty string.", "file_type": "rationale", "source_file": "tests/test_contextual_prefix.py", "source_location": "L101"}, {"id": "test_contextual_prefix_rationale_114", "label": "Second call should use cache, not call get_creator_data again.", "file_type": "rationale", "source_file": "tests/test_contextual_prefix.py", "source_location": "L114"}, {"id": "test_contextual_prefix_rationale_125", "label": "Prefix should not exceed 500 characters.", "file_type": "rationale", "source_file": "tests/test_contextual_prefix.py", "source_location": "L125"}, {"id": "test_contextual_prefix_rationale_138", "label": "Formal creators should get a style hint in prefix.", "file_type": "rationale", "source_file": "tests/test_contextual_prefix.py", "source_location": "L138"}, {"id": "test_contextual_prefix_rationale_148", "label": "Italian creators should get Italian language label.", "file_type": "rationale", "source_file": "tests/test_contextual_prefix.py", "source_location": "L148"}, {"id": "test_contextual_prefix_rationale_168", "label": "DB failures should return empty string, not crash.", "file_type": "rationale", "source_file": "tests/test_contextual_prefix.py", "source_location": "L168"}, {"id": "test_contextual_prefix_rationale_175", "label": "When knowledge_about is empty, derive domain from product names.", "file_type": "rationale", "source_file": "tests/test_contextual_prefix.py", "source_location": "L175"}, {"id": "test_contextual_prefix_rationale_196", "label": "When no specialties, bio, or products \u2014 use FAQ topics.", "file_type": "rationale", "source_file": "tests/test_contextual_prefix.py", "source_location": "L196"}, {"id": "test_contextual_prefix_rationale_214", "label": "Test the embedding wrapper functions.", "file_type": "rationale", "source_file": "tests/test_contextual_prefix.py", "source_location": "L214"}, {"id": "test_contextual_prefix_rationale_223", "label": "Should prepend prefix to text before generating embedding.", "file_type": "rationale", "source_file": "tests/test_contextual_prefix.py", "source_location": "L223"}, {"id": "test_contextual_prefix_rationale_239", "label": "When prefix is empty, should just embed the raw text.", "file_type": "rationale", "source_file": "tests/test_contextual_prefix.py", "source_location": "L239"}, {"id": "test_contextual_prefix_rationale_254", "label": "Batch variant should prepend prefix to all texts.", "file_type": "rationale", "source_file": "tests/test_contextual_prefix.py", "source_location": "L254"}, {"id": "test_contextual_prefix_rationale_270", "label": "Verify search queries do NOT get the contextual prefix.", "file_type": "rationale", "source_file": "tests/test_contextual_prefix.py", "source_location": "L270"}, {"id": "test_contextual_prefix_rationale_273", "label": "SemanticRAG._semantic_search should call generate_embedding, not _with_context.", "file_type": "rationale", "source_file": "tests/test_contextual_prefix.py", "source_location": "L273"}], "edges": [{"source": "test_contextual_prefix", "target": "pytest", "relation": "imports", "confidence": "EXTRACTED", "source_file": "tests/test_contextual_prefix.py", "source_location": "L10", "weight": 1.0}, {"source": "test_contextual_prefix", "target": "unittest_mock", "relation": "imports_from", "confidence": "EXTRACTED", "source_file": "tests/test_contextual_prefix.py", "source_location": "L11", "weight": 1.0}, {"source": "test_contextual_prefix", "target": "dataclasses", "relation": "imports_from", "confidence": "EXTRACTED", "source_file": "tests/test_contextual_prefix.py", "source_location": "L12", "weight": 1.0}, {"source": "test_contextual_prefix", "target": "typing", "relation": "imports_from", "confidence": "EXTRACTED", "source_file": "tests/test_contextual_prefix.py", "source_location": "L13", "weight": 1.0}, {"source": "test_contextual_prefix", "target": "test_contextual_prefix_make_creator_data", "relation": "contains", "confidence": "EXTRACTED", "source_file": "tests/test_contextual_prefix.py", "source_location": "L16", "weight": 1.0}, {"source": "test_contextual_prefix", "target": "test_contextual_prefix_testbuildcontextualprefix", "relation": "contains", "confidence": "EXTRACTED", "source_file": "tests/test_contextual_prefix.py", "source_location": "L54", "weight": 1.0}, {"source": "test_contextual_prefix_testbuildcontextualprefix", "target": "test_contextual_prefix_testbuildcontextualprefix_setup_method", "relation": "method", "confidence": "EXTRACTED", "source_file": "tests/test_contextual_prefix.py", "source_location": "L57", "weight": 1.0}, {"source": "test_contextual_prefix", "target": "test_contextual_prefix_test_full_data_prefix", "relation": "contains", "confidence": "EXTRACTED", "source_file": "tests/test_contextual_prefix.py", "source_location": "L63", "weight": 1.0}, {"source": "test_contextual_prefix", "target": "test_contextual_prefix_test_missing_specialties_uses_bio", "relation": "contains", "confidence": "EXTRACTED", "source_file": "tests/test_contextual_prefix.py", "source_location": "L78", "weight": 1.0}, {"source": "test_contextual_prefix", "target": "test_contextual_prefix_test_missing_all_knowledge_about", "relation": "contains", "confidence": "EXTRACTED", "source_file": "tests/test_contextual_prefix.py", "source_location": "L90", "weight": 1.0}, {"source": "test_contextual_prefix", "target": "test_contextual_prefix_test_no_creator_returns_empty", "relation": "contains", "confidence": "EXTRACTED", "source_file": "tests/test_contextual_prefix.py", "source_location": "L100", "weight": 1.0}, {"source": "test_contextual_prefix", "target": "test_contextual_prefix_test_prefix_is_cached", "relation": "contains", "confidence": "EXTRACTED", "source_file": "tests/test_contextual_prefix.py", "source_location": "L113", "weight": 1.0}, {"source": "test_contextual_prefix", "target": "test_contextual_prefix_test_prefix_capped_at_500_chars", "relation": "contains", "confidence": "EXTRACTED", "source_file": "tests/test_contextual_prefix.py", "source_location": "L124", "weight": 1.0}, {"source": "test_contextual_prefix", "target": "test_contextual_prefix_test_formal_style_mentioned", "relation": "contains", "confidence": "EXTRACTED", "source_file": "tests/test_contextual_prefix.py", "source_location": "L137", "weight": 1.0}, {"source": "test_contextual_prefix", "target": "test_contextual_prefix_test_italian_dialect", "relation": "contains", "confidence": "EXTRACTED", "source_file": "tests/test_contextual_prefix.py", "source_location": "L147", "weight": 1.0}, {"source": "test_contextual_prefix", "target": "test_contextual_prefix_test_db_error_returns_empty", "relation": "contains", "confidence": "EXTRACTED", "source_file": "tests/test_contextual_prefix.py", "source_location": "L167", "weight": 1.0}, {"source": "test_contextual_prefix", "target": "test_contextual_prefix_test_product_fallback_when_no_specialties", "relation": "contains", "confidence": "EXTRACTED", "source_file": "tests/test_contextual_prefix.py", "source_location": "L174", "weight": 1.0}, {"source": "test_contextual_prefix", "target": "test_contextual_prefix_test_faq_fallback_when_only_name", "relation": "contains", "confidence": "EXTRACTED", "source_file": "tests/test_contextual_prefix.py", "source_location": "L195", "weight": 1.0}, {"source": "test_contextual_prefix", "target": "test_contextual_prefix_testgenerateembeddingwithcontext", "relation": "contains", "confidence": "EXTRACTED", "source_file": "tests/test_contextual_prefix.py", "source_location": "L213", "weight": 1.0}, {"source": "test_contextual_prefix_testgenerateembeddingwithcontext", "target": "test_contextual_prefix_testgenerateembeddingwithcontext_setup_method", "relation": "method", "confidence": "EXTRACTED", "source_file": "tests/test_contextual_prefix.py", "source_location": "L216", "weight": 1.0}, {"source": "test_contextual_prefix", "target": "test_contextual_prefix_test_prepends_prefix", "relation": "contains", "confidence": "EXTRACTED", "source_file": "tests/test_contextual_prefix.py", "source_location": "L222", "weight": 1.0}, {"source": "test_contextual_prefix", "target": "test_contextual_prefix_test_empty_prefix_passes_text_only", "relation": "contains", "confidence": "EXTRACTED", "source_file": "tests/test_contextual_prefix.py", "source_location": "L238", "weight": 1.0}, {"source": "test_contextual_prefix", "target": "test_contextual_prefix_test_batch_prepends_to_all", "relation": "contains", "confidence": "EXTRACTED", "source_file": "tests/test_contextual_prefix.py", "source_location": "L253", "weight": 1.0}, {"source": "test_contextual_prefix", "target": "test_contextual_prefix_testsearchqueriesnotprefixed", "relation": "contains", "confidence": "EXTRACTED", "source_file": "tests/test_contextual_prefix.py", "source_location": "L269", "weight": 1.0}, {"source": "test_contextual_prefix_testsearchqueriesnotprefixed", "target": "test_contextual_prefix_testsearchqueriesnotprefixed_test_semantic_search_uses_raw_embedding", "relation": "method", "confidence": "EXTRACTED", "source_file": "tests/test_contextual_prefix.py", "source_location": "L272", "weight": 1.0}, {"source": "test_contextual_prefix_test_full_data_prefix", "target": "test_contextual_prefix_make_creator_data", "relation": "calls", "confidence": "EXTRACTED", "source_file": "tests/test_contextual_prefix.py", "source_location": "L66", "weight": 1.0}, {"source": "test_contextual_prefix_test_missing_specialties_uses_bio", "target": "test_contextual_prefix_make_creator_data", "relation": "calls", "confidence": "EXTRACTED", "source_file": "tests/test_contextual_prefix.py", "source_location": "L81", "weight": 1.0}, {"source": "test_contextual_prefix_test_missing_all_knowledge_about", "target": "test_contextual_prefix_make_creator_data", "relation": "calls", "confidence": "EXTRACTED", "source_file": "tests/test_contextual_prefix.py", "source_location": "L93", "weight": 1.0}, {"source": "test_contextual_prefix_test_prefix_is_cached", "target": "test_contextual_prefix_make_creator_data", "relation": "calls", "confidence": "EXTRACTED", "source_file": "tests/test_contextual_prefix.py", "source_location": "L116", "weight": 1.0}, {"source": "test_contextual_prefix_test_prefix_capped_at_500_chars", "target": "test_contextual_prefix_make_creator_data", "relation": "calls", "confidence": "EXTRACTED", "source_file": "tests/test_contextual_prefix.py", "source_location": "L127", "weight": 1.0}, {"source": "test_contextual_prefix_test_formal_style_mentioned", "target": "test_contextual_prefix_make_creator_data", "relation": "calls", "confidence": "EXTRACTED", "source_file": "tests/test_contextual_prefix.py", "source_location": "L140", "weight": 1.0}, {"source": "test_contextual_prefix_test_italian_dialect", "target": "test_contextual_prefix_make_creator_data", "relation": "calls", "confidence": "EXTRACTED", "source_file": "tests/test_contextual_prefix.py", "source_location": "L150", "weight": 1.0}, {"source": "test_contextual_prefix_test_product_fallback_when_no_specialties", "target": "test_contextual_prefix_make_creator_data", "relation": "calls", "confidence": "EXTRACTED", "source_file": "tests/test_contextual_prefix.py", "source_location": "L183", "weight": 1.0}, {"source": "test_contextual_prefix_test_faq_fallback_when_only_name", "target": "test_contextual_prefix_make_creator_data", "relation": "calls", "confidence": "EXTRACTED", "source_file": "tests/test_contextual_prefix.py", "source_location": "L203", "weight": 1.0}, {"source": "test_contextual_prefix_test_prepends_prefix", "target": "test_contextual_prefix_make_creator_data", "relation": "calls", "confidence": "EXTRACTED", "source_file": "tests/test_contextual_prefix.py", "source_location": "L225", "weight": 1.0}, {"source": "test_contextual_prefix_test_batch_prepends_to_all", "target": "test_contextual_prefix_make_creator_data", "relation": "calls", "confidence": "EXTRACTED", "source_file": "tests/test_contextual_prefix.py", "source_location": "L256", "weight": 1.0}, {"source": "test_contextual_prefix_rationale_1", "target": "test_contextual_prefix", "relation": "rationale_for", "confidence": "EXTRACTED", "source_file": "tests/test_contextual_prefix.py", "source_location": "L1", "weight": 1.0}, {"source": "test_contextual_prefix_rationale_25", "target": "test_contextual_prefix_make_creator_data", "relation": "rationale_for", "confidence": "EXTRACTED", "source_file": "tests/test_contextual_prefix.py", "source_location": "L25", "weight": 1.0}, {"source": "test_contextual_prefix_rationale_55", "target": "test_contextual_prefix_testbuildcontextualprefix", "relation": "rationale_for", "confidence": "EXTRACTED", "source_file": "tests/test_contextual_prefix.py", "source_location": "L55", "weight": 1.0}, {"source": "test_contextual_prefix_rationale_58", "target": "test_contextual_prefix_testbuildcontextualprefix_setup_method", "relation": "rationale_for", "confidence": "EXTRACTED", "source_file": "tests/test_contextual_prefix.py", "source_location": "L58", "weight": 1.0}, {"source": "test_contextual_prefix_rationale_64", "target": "test_contextual_prefix_testbuildcontextualprefix_test_full_data_prefix", "relation": "rationale_for", "confidence": "EXTRACTED", "source_file": "tests/test_contextual_prefix.py", "source_location": "L64", "weight": 1.0}, {"source": "test_contextual_prefix_rationale_79", "target": "test_contextual_prefix_testbuildcontextualprefix_test_missing_specialties_uses_bio", "relation": "rationale_for", "confidence": "EXTRACTED", "source_file": "tests/test_contextual_prefix.py", "source_location": "L79", "weight": 1.0}, {"source": "test_contextual_prefix_rationale_91", "target": "test_contextual_prefix_testbuildcontextualprefix_test_missing_all_knowledge_about", "relation": "rationale_for", "confidence": "EXTRACTED", "source_file": "tests/test_contextual_prefix.py", "source_location": "L91", "weight": 1.0}, {"source": "test_contextual_prefix_rationale_101", "target": "test_contextual_prefix_testbuildcontextualprefix_test_no_creator_returns_empty", "relation": "rationale_for", "confidence": "EXTRACTED", "source_file": "tests/test_contextual_prefix.py", "source_location": "L101", "weight": 1.0}, {"source": "test_contextual_prefix_rationale_114", "target": "test_contextual_prefix_testbuildcontextualprefix_test_prefix_is_cached", "relation": "rationale_for", "confidence": "EXTRACTED", "source_file": "tests/test_contextual_prefix.py", "source_location": "L114", "weight": 1.0}, {"source": "test_contextual_prefix_rationale_125", "target": "test_contextual_prefix_testbuildcontextualprefix_test_prefix_capped_at_500_chars", "relation": "rationale_for", "confidence": "EXTRACTED", "source_file": "tests/test_contextual_prefix.py", "source_location": "L125", "weight": 1.0}, {"source": "test_contextual_prefix_rationale_138", "target": "test_contextual_prefix_testbuildcontextualprefix_test_formal_style_mentioned", "relation": "rationale_for", "confidence": "EXTRACTED", "source_file": "tests/test_contextual_prefix.py", "source_location": "L138", "weight": 1.0}, {"source": "test_contextual_prefix_rationale_148", "target": "test_contextual_prefix_testbuildcontextualprefix_test_italian_dialect", "relation": "rationale_for", "confidence": "EXTRACTED", "source_file": "tests/test_contextual_prefix.py", "source_location": "L148", "weight": 1.0}, {"source": "test_contextual_prefix_rationale_168", "target": "test_contextual_prefix_testbuildcontextualprefix_test_db_error_returns_empty", "relation": "rationale_for", "confidence": "EXTRACTED", "source_file": "tests/test_contextual_prefix.py", "source_location": "L168", "weight": 1.0}, {"source": "test_contextual_prefix_rationale_175", "target": "test_contextual_prefix_testbuildcontextualprefix_test_product_fallback_when_no_specialties", "relation": "rationale_for", "confidence": "EXTRACTED", "source_file": "tests/test_contextual_prefix.py", "source_location": "L175", "weight": 1.0}, {"source": "test_contextual_prefix_rationale_196", "target": "test_contextual_prefix_testbuildcontextualprefix_test_faq_fallback_when_only_name", "relation": "rationale_for", "confidence": "EXTRACTED", "source_file": "tests/test_contextual_prefix.py", "source_location": "L196", "weight": 1.0}, {"source": "test_contextual_prefix_rationale_214", "target": "test_contextual_prefix_testgenerateembeddingwithcontext", "relation": "rationale_for", "confidence": "EXTRACTED", "source_file": "tests/test_contextual_prefix.py", "source_location": "L214", "weight": 1.0}, {"source": "test_contextual_prefix_rationale_223", "target": "test_contextual_prefix_testgenerateembeddingwithcontext_test_prepends_prefix", "relation": "rationale_for", "confidence": "EXTRACTED", "source_file": "tests/test_contextual_prefix.py", "source_location": "L223", "weight": 1.0}, {"source": "test_contextual_prefix_rationale_239", "target": "test_contextual_prefix_testgenerateembeddingwithcontext_test_empty_prefix_passes_text_only", "relation": "rationale_for", "confidence": "EXTRACTED", "source_file": "tests/test_contextual_prefix.py", "source_location": "L239", "weight": 1.0}, {"source": "test_contextual_prefix_rationale_254", "target": "test_contextual_prefix_testgenerateembeddingwithcontext_test_batch_prepends_to_all", "relation": "rationale_for", "confidence": "EXTRACTED", "source_file": "tests/test_contextual_prefix.py", "source_location": "L254", "weight": 1.0}, {"source": "test_contextual_prefix_rationale_270", "target": "test_contextual_prefix_testsearchqueriesnotprefixed", "relation": "rationale_for", "confidence": "EXTRACTED", "source_file": "tests/test_contextual_prefix.py", "source_location": "L270", "weight": 1.0}, {"source": "test_contextual_prefix_rationale_273", "target": "test_contextual_prefix_testsearchqueriesnotprefixed_test_semantic_search_uses_raw_embedding", "relation": "rationale_for", "confidence": "EXTRACTED", "source_file": "tests/test_contextual_prefix.py", "source_location": "L273", "weight": 1.0}]}