{"nodes": [{"id": "creator", "label": "creator.py", "file_type": "code", "source_file": "api/models/creator.py", "source_location": "L1"}, {"id": "creator_creator", "label": "Creator", "file_type": "code", "source_file": "api/models/creator.py", "source_location": "L28"}, {"id": "base", "label": "Base", "file_type": "code", "source_file": "", "source_location": ""}, {"id": "creator_creatoravailability", "label": "CreatorAvailability", "file_type": "code", "source_file": "api/models/creator.py", "source_location": "L107"}, {"id": "creator_toneprofile", "label": "ToneProfile", "file_type": "code", "source_file": "api/models/creator.py", "source_location": "L122"}, {"id": "creator_styleprofilemodel", "label": "StyleProfileModel", "file_type": "code", "source_file": "api/models/creator.py", "source_location": "L139"}, {"id": "creator_personalitydoc", "label": "PersonalityDoc", "file_type": "code", "source_file": "api/models/creator.py", "source_location": "L163"}, {"id": "creator_relationshipdnamodel", "label": "RelationshipDNAModel", "file_type": "code", "source_file": "api/models/creator.py", "source_location": "L188"}, {"id": "creator_rationale_1", "label": "Creator models: Creator, CreatorAvailability, ToneProfile, StyleProfileModel, Pe", "file_type": "rationale", "source_file": "api/models/creator.py", "source_location": "L1"}, {"id": "creator_rationale_108", "label": "Creator's weekly availability schedule", "file_type": "rationale", "source_file": "api/models/creator.py", "source_location": "L108"}, {"id": "creator_rationale_123", "label": "Creator's voice/personality profile for AI clone.     Migrated from data/tone_pr", "file_type": "rationale", "source_file": "api/models/creator.py", "source_location": "L123"}, {"id": "creator_rationale_140", "label": "Data-driven style profile extracted by StyleAnalyzer.      Stores quantitative m", "file_type": "rationale", "source_file": "api/models/creator.py", "source_location": "L140"}, {"id": "creator_rationale_164", "label": "Persistent storage for personality extraction documents (Doc D, Doc E).      Rai", "file_type": "rationale", "source_file": "api/models/creator.py", "source_location": "L164"}, {"id": "creator_rationale_189", "label": "SQLAlchemy model for relationship-specific communication context.      Stores pe", "file_type": "rationale", "source_file": "api/models/creator.py", "source_location": "L189"}], "edges": [{"source": "creator", "target": "uuid", "relation": "imports", "confidence": "EXTRACTED", "source_file": "api/models/creator.py", "source_location": "L2", "weight": 1.0}, {"source": "creator", "target": "sqlalchemy", "relation": "imports_from", "confidence": "EXTRACTED", "source_file": "api/models/creator.py", "source_location": "L4", "weight": 1.0}, {"source": "creator", "target": "sqlalchemy_dialects_postgresql", "relation": "imports_from", "confidence": "EXTRACTED", "source_file": "api/models/creator.py", "source_location": "L18", "weight": 1.0}, {"source": "creator", "target": "sqlalchemy_orm", "relation": "imports_from", "confidence": "EXTRACTED", "source_file": "api/models/creator.py", "source_location": "L19", "weight": 1.0}, {"source": "creator", "target": "sqlalchemy_sql", "relation": "imports_from", "confidence": "EXTRACTED", "source_file": "api/models/creator.py", "source_location": "L20", "weight": 1.0}, {"source": "creator", "target": "api_database", "relation": "imports_from", "confidence": "EXTRACTED", "source_file": "api/models/creator.py", "source_location": "L23", "weight": 1.0}, {"source": "creator", "target": "database", "relation": "imports_from", "confidence": "EXTRACTED", "source_file": "api/models/creator.py", "source_location": "L25", "weight": 1.0}, {"source": "creator", "target": "creator_creator", "relation": "contains", "confidence": "EXTRACTED", "source_file": "api/models/creator.py", "source_location": "L28", "weight": 1.0}, {"source": "creator_creator", "target": "base", "relation": "inherits", "confidence": "EXTRACTED", "source_file": "api/models/creator.py", "source_location": "L28", "weight": 1.0}, {"source": "creator", "target": "creator_creatoravailability", "relation": "contains", "confidence": "EXTRACTED", "source_file": "api/models/creator.py", "source_location": "L107", "weight": 1.0}, {"source": "creator_creatoravailability", "target": "base", "relation": "inherits", "confidence": "EXTRACTED", "source_file": "api/models/creator.py", "source_location": "L107", "weight": 1.0}, {"source": "creator", "target": "creator_toneprofile", "relation": "contains", "confidence": "EXTRACTED", "source_file": "api/models/creator.py", "source_location": "L122", "weight": 1.0}, {"source": "creator_toneprofile", "target": "base", "relation": "inherits", "confidence": "EXTRACTED", "source_file": "api/models/creator.py", "source_location": "L122", "weight": 1.0}, {"source": "creator", "target": "creator_styleprofilemodel", "relation": "contains", "confidence": "EXTRACTED", "source_file": "api/models/creator.py", "source_location": "L139", "weight": 1.0}, {"source": "creator_styleprofilemodel", "target": "base", "relation": "inherits", "confidence": "EXTRACTED", "source_file": "api/models/creator.py", "source_location": "L139", "weight": 1.0}, {"source": "creator", "target": "creator_personalitydoc", "relation": "contains", "confidence": "EXTRACTED", "source_file": "api/models/creator.py", "source_location": "L163", "weight": 1.0}, {"source": "creator_personalitydoc", "target": "base", "relation": "inherits", "confidence": "EXTRACTED", "source_file": "api/models/creator.py", "source_location": "L163", "weight": 1.0}, {"source": "creator", "target": "creator_relationshipdnamodel", "relation": "contains", "confidence": "EXTRACTED", "source_file": "api/models/creator.py", "source_location": "L188", "weight": 1.0}, {"source": "creator_relationshipdnamodel", "target": "base", "relation": "inherits", "confidence": "EXTRACTED", "source_file": "api/models/creator.py", "source_location": "L188", "weight": 1.0}, {"source": "creator_rationale_1", "target": "creator", "relation": "rationale_for", "confidence": "EXTRACTED", "source_file": "api/models/creator.py", "source_location": "L1", "weight": 1.0}, {"source": "creator_rationale_108", "target": "creator_creatoravailability", "relation": "rationale_for", "confidence": "EXTRACTED", "source_file": "api/models/creator.py", "source_location": "L108", "weight": 1.0}, {"source": "creator_rationale_123", "target": "creator_toneprofile", "relation": "rationale_for", "confidence": "EXTRACTED", "source_file": "api/models/creator.py", "source_location": "L123", "weight": 1.0}, {"source": "creator_rationale_140", "target": "creator_styleprofilemodel", "relation": "rationale_for", "confidence": "EXTRACTED", "source_file": "api/models/creator.py", "source_location": "L140", "weight": 1.0}, {"source": "creator_rationale_164", "target": "creator_personalitydoc", "relation": "rationale_for", "confidence": "EXTRACTED", "source_file": "api/models/creator.py", "source_location": "L164", "weight": 1.0}, {"source": "creator_rationale_189", "target": "creator_relationshipdnamodel", "relation": "rationale_for", "confidence": "EXTRACTED", "source_file": "api/models/creator.py", "source_location": "L189", "weight": 1.0}]}